django_charting/__init__.py
django_charting/charts.py
django_charting/columns.py
django_charting/utils.py
django_charting/templates/charts/chart.html
django_charting/templatetags/__init__.py
django_charting/templatetags/charting.py
django_charting/templatetags/charts.py
django_charting/templatetags/django_charting.py
tests/app/__init__.py
tests/app/settings.py
tests/app/urls.py
django_charting-22.1.dist-info/AUTHORS
django_charting-22.1.dist-info/LICENSE
django_charting-22.1.dist-info/METADATA
django_charting-22.1.dist-info/WHEEL
django_charting-22.1.dist-info/top_level.txt
django_charting-22.1.dist-info/RECORD
